MicrosoftHealth/Exceptions.py
MicrosoftHealth/MicrosoftHealth.py
MicrosoftHealth/__init__.py
MicrosoftHealth-0.1.0.dist-info/DESCRIPTION.rst
MicrosoftHealth-0.1.0.dist-info/METADATA
MicrosoftHealth-0.1.0.dist-info/RECORD
MicrosoftHealth-0.1.0.dist-info/WHEEL
MicrosoftHealth-0.1.0.dist-info/metadata.json
MicrosoftHealth-0.1.0.dist-info/top_level.txt
